setup.py
bin/srccat
srccat/__init__.py
srccat/extension_language_index.py
srccat/language_association.py
srccat/mappings.py
srccat/srccat.py
srccat.egg-info/PKG-INFO
srccat.egg-info/SOURCES.txt
srccat.egg-info/dependency_links.txt
srccat.egg-info/not-zip-safe
srccat.egg-info/requires.txt
srccat.egg-info/top_level.txt
tests/__init__.py
tests/test_language_association.py