Metadata-Version: 1.0
Name: srccat
Version: 0.3.1
Summary: Syntax highlights source code to terminal using colout
Home-page: http://cfeduke.github.com/srccat/
Author: cfeduke
Author-email: charles.feduke@gmail.com
License: GPL
Platform: UNKNOWN
